Easy_GRID/CPU_Agents.py
Easy_GRID/CPU_ClassFun.py
Easy_GRID/GUI_Anchor.py
Easy_GRID/GUI_ClassFun.py
Easy_GRID/GUI_Cropper.py
Easy_GRID/GUI_Input.py
Easy_GRID/GUI_Kmeaner.py
Easy_GRID/GUI_Main.py
Easy_GRID/GUI_Output.py
Easy_GRID/__init__.py
Easy_GRID/__main__.py
Easy_GRID-0.0.13.dist-info/METADATA
Easy_GRID-0.0.13.dist-info/WHEEL
Easy_GRID-0.0.13.dist-info/top_level.txt
Easy_GRID-0.0.13.dist-info/RECORD
