Metadata-Version: 2.1
Name: Easy-GRID
Version: 0.0.13
Summary: A GUI for field segmentation
Home-page: https://github.com/Zhiwu-Zhang-Lab/James_Git
Author: James Chen
Author-email: chun-peng.chen@wsu.edu
License: MIT
Platform: UNKNOWN
Requires-Dist: numpy
Requires-Dist: pandas (>=0.19.2)
Requires-Dist: sklearn
Requires-Dist: scipy
Requires-Dist: opencv-python
Requires-Dist: image
Requires-Dist: PyQt5
Requires-Dist: tqdm
